b64steg/B64steger.py
b64steg/__init__.py
b64steg-1.0.0.dist-info/LICENSE
b64steg-1.0.0.dist-info/METADATA
b64steg-1.0.0.dist-info/WHEEL
b64steg-1.0.0.dist-info/top_level.txt
b64steg-1.0.0.dist-info/RECORD
