Metadata-Version: 2.1
Name: b64steg
Version: 1.0.0
Summary: base64 Steganography
Home-page: https://github.com/Mz1z/b64steg
Author: Mz1
Author-email: mzi_mzi@163.com
License: UNKNOWN
Platform: UNKNOWN
Classifier: Programming Language :: Python :: 3
Classifier: License :: OSI Approved :: MIT License
Classifier: Operating System :: OS Independent
Requires-Python: >=3.4
License-File: LICENSE
